{
    "Thoughts": [
        {"Idea": "We have put together I think the most extensive and inclusive voter fraud organization in the history of american politics!", "Link": "https://www.youtube.com/watch?v=MA8a2g6tTp0"}
    ],
    "Triggers": [
        "biden",
        "democrats",
        "demokraa",
        "hunter",
        "blm",
        "sosialism",
        "socialism"
    ],
    "FrontalCortexResponses": [
        "C'mon man!",
        "Oh shut up man!",
        "Gimme a break!",
        "Bunch of malarkey!",
        "Let's focus on winning Trump!"
    ]
}